{
  "id": "15356",
  "stock": "15356",
  "title": "2006 HAAS EC-1600-4x",
  "year": "2006",
  "brand": "HAAS",
  "model": "EC-1600-4x",
  "category_id": 2,
  "category_name": "Centros de Mecanizado CNC",
  "category_slug": "2-cnc-machining-centers",
  "image_url": "https://machine-hub-prod.s3.amazonaws.com/machine-listing-images/f2f52c41df6c7a80dd89f592f245a9d8-cfe2dfbfb1d5488d8fd0cecad2cab03b.jpg",
  "machine_slug": "15356/2006-haas-ec-1600-4x",
  "specs": {
    "CNC Control": "Yes",
    "Type Of CNC Control": "Haas",
    "# Axis": "4",
    "Table Size": "64\" x 32\"",
    "Pallet Diameter": "30\" Round Diameter",
    "Pallet Capacity": "10000 pounds",
    "Pallet Indexing (B-Axis)": "0.001°",
    "X": "64 inches",
    "Y": "50 inches",
    "Z": "32 inches",
    "Rapid Traverse Rate (X/Y/Z)": "600 ipm",
    "Spindle Taper": "CAT 50",
    "Spindle Speed": "7,500 rpm",
    "Main Motor": "30 hp",
    "Coolant Thru Spindle": "Yes",
    "Tool Changer Capacity": "50",
    "Weight": "30000 pounds"
  },
  "description": "The HAAS EC-1600-4x is an exclusive part of our Machining Centers, Horizontal inventory which we own and service. We're the international CNC specialists with the best guarantee in the industry.",
  "images": [
    "https://machine-hub-prod.s3.amazonaws.com/machine-listing-images/f2f52c41df6c7a80dd89f592f245a9d8-cfe2dfbfb1d5488d8fd0cecad2cab03b.jpg",
    "https://machine-hub-prod.s3.amazonaws.com/machine-listing-images/f507783927f2ec2737ba40afbd17efb5-59721e66618960fdfe7369591fc8e196.jpg",
    "https://machine-hub-prod.s3.amazonaws.com/machine-listing-images/5d6d1c0e9be7aeea751074bc7b4cfbfa-4467582ecbdd3d30e6b4b07b07e1bd05.jpg",
    "https://machine-hub-prod.s3.amazonaws.com/machine-listing-images/f8d6a4c1e7b1da8be2af46413260f12d-cfe2dfbfb1d5488d8fd0cecad2cab03b.jpg",
    "https://machine-hub-prod.s3.amazonaws.com/machine-listing-images/3a413cab4a1b175a1b32871e890417ca-50ff3b63256a860b00b783603db7b9b4.jpg"
  ]
}